{
  "site": "Trang Cập Nhật Tin Tức Mỗi Ngày",
  "operator": "Phuc Hung Agent",
  "last_updated": "2026-06-28",
  "news_list": [
    {
      "date": "2026-06-28",
      "title": "Thị trường reform nhà ở Nhật 2024 đạt 7.347 tỷ yên, dự báo 2025 đi ngang nhẹ"
    },
    {
      "date": "2026-06-27",
      "title": "Giá thuê nhà theo ga trên tuyến JR Yamanote (Tokyo): Yurakucho đắt nhất, Tabata rẻ nhất"
    },
    {
      "date": "2026-06-26",
      "title": "Thị trường văn phòng cho thuê Nhật (T5/2026): Tokyo tỷ lệ trống còn 2.07%, giá thuê tăng gần 10%"
    },
    {
      "date": "2026-06-25",
      "title": "Lương trung bình người Nhật năm 2024 đạt 478万円 (+3.9%): nam 587, nữ 333"
    },
    {
      "date": "2026-06-24",
      "title": "Cải cách thuế thừa kế BĐS Nhật: từ 2027, BĐS mua trong 5 năm trước thừa kế bị đánh giá theo giá thị trường"
    }
  ]
}
